setup.py
unclebob/__init__.py
unclebob/models.py
unclebob/monkey.py
unclebob/options.py
unclebob/runners.py
unclebob/version.py
unclebob/views.py
unclebob.egg-info/PKG-INFO
unclebob.egg-info/SOURCES.txt
unclebob.egg-info/dependency_links.txt
unclebob.egg-info/requires.txt
unclebob.egg-info/top_level.txt
unclebob/management/__init__.py
unclebob/management/commands/__init__.py
unclebob/management/commands/test.py