Metadata-Version: 1.0
Name: unclebob
Version: 0.3.7
Summary: Django testing tool set
Home-page: http://github.com/gabrielfalcao/unclebob
Author: Gabriel Falcao
Author-email: gabriel@nacaolivre.org
License: UNKNOWN
Platform: UNKNOWN
